rework_ui/__init__.py
rework_ui/app.py
rework_ui/blueprint.py
rework_ui/cli.py
rework_ui/helper.py
rework_ui/schema.py
rework_ui/schema.sql
rework_ui/rui_static/info.js
rework_ui/rui_static/logview.js
rework_ui/rui_static/rework_ui_elm.js
rework_ui/rui_static/style.css
rework_ui/rui_templates/rui_base.html
rework_ui/rui_templates/rui_home.html
rework_ui/rui_templates/taskerror.html
rework_ui/rui_templates/taskinfo.html
rework_ui/rui_templates/tasklogs.html
rework_ui-0.16.0.dist-info/METADATA
rework_ui-0.16.0.dist-info/WHEEL
rework_ui-0.16.0.dist-info/entry_points.txt
rework_ui-0.16.0.dist-info/top_level.txt
rework_ui-0.16.0.dist-info/RECORD
