Metadata-Version: 2.1
Name: rework_ui
Version: 0.16.0
Summary: A web ui for the rework distributed task dispatcher
Home-page: https://hg.sr.ht/~pythonian/rework_ui
Author: Aurelien Campeas
Author-email: aurelien.campeas@pythonian.fr
Classifier: Development Status :: 4 - Beta
Classifier: Intended Audience :: Developers
Classifier: License :: OSI Approved :: GNU Lesser General Public License v3 (LGPLv3)
Classifier: Operating System :: OS Independent
Classifier: Programming Language :: Python :: 3
Classifier: Programming Language :: ML
Classifier: Environment :: Web Environment
Classifier: Topic :: System :: Distributed Computing
Classifier: Topic :: Software Development :: User Interfaces
Requires-Dist: rework
Requires-Dist: flask
Requires-Dist: python-icron
Requires-Dist: pygments
Requires-Dist: werkzeug >=2.3.7
Requires-Dist: lxml
Requires-Dist: sqlalchemy
